dvd_logofier/__init__.py
dvd_logofier/__main__.py
dvd_logofier/cli.py
dvd_logofier/dvd_logofier.py
dvd_logofier-0.1.0.dist-info/METADATA
dvd_logofier-0.1.0.dist-info/WHEEL
dvd_logofier-0.1.0.dist-info/entry_points.txt
dvd_logofier-0.1.0.dist-info/RECORD
