Metadata-Version: 2.4
Name: dvd_logofier
Version: 0.1.0
Summary: A small package to simulate the DVD bounce for every image (or series of images) on any screen resolution
Project-URL: Homepage, https://github.com/SpeedyNurBesser/dvd_logofier
Project-URL: Issues, https://github.com/SpeedyNurBesser/dvd_logofier/issues
Author-email: Ole370 <370.Ole@proton.me>
License: MIT
Classifier: Operating System :: OS Independent
Classifier: Programming Language :: Python :: 3
Requires-Python: >=3.9
